crontzconvert.py
crontzconvert-0.1.2.dist-info/LICENSE
crontzconvert-0.1.2.dist-info/METADATA
crontzconvert-0.1.2.dist-info/WHEEL
crontzconvert-0.1.2.dist-info/top_level.txt
crontzconvert-0.1.2.dist-info/RECORD
