Metadata-Version: 2.1
Name: crontzconvert
Version: 0.1.2
Summary: Change crontab between two timezones.
Home-page: https://github.com/vidocqh/cron-timezone-convert
Author: Vidocq
Author-email: vidocqho@gmail.com
License: MIT
Platform: UNKNOWN
Classifier: Programming Language :: Python :: 3
Classifier: License :: OSI Approved :: MIT License
Classifier: Operating System :: OS Independent
Requires-Python: >=3.6
Requires-Dist: pytz
